[
  { "time": 0.334, "move": "samba1" },
  { "time": 0.601, "move": "samba2" },
  { "time": 0.865, "move": "samba4" },
  { "time": 1.219, "move": "samba2" },
  { "time": 1.684, "move": "samba2" },
  { "time": 2.017, "move": "samba4" },
  { "time": 2.551, "move": "samba2" },
  { "time": 3.03, "move": "samba2" },
  { "time": 3.352, "move": "samba4" },
  { "time": 3.884, "move": "samba2" },
  { "time": 4.352, "move": "samba2" },
  { "time": 4.696, "move": "samba2" },
  { "time": 5.219, "move": "samba2" },
  { "time": 5.687, "move": "samba2" },
  { "time": 6.017, "move": "samba2" },
  { "time": 6.702, "move": "samba2" },
  { "time": 7.37, "move": "samba2" },
  { "time": 7.918, "move": "samba4" },
  { "time": 8.182, "move": "samba4" },
  { "time": 8.696, "move": "samba3" },
  { "time": 9.25, "move": "samba4" },
  { "time": 9.517, "move": "samba4" },
  { "time": 10.038, "move": "samba1" },
  { "time": 10.551, "move": "samba4" },
  { "time": 10.818, "move": "samba2" },
  { "time": 11.384, "move": "samba1" },
  { "time": 12.034, "move": "samba3" },
  { "time": 12.716, "move": "samba1" },
  { "time": 13.369, "move": "samba3" },
  { "time": 14.039, "move": "samba1" },
  { "time": 14.701, "move": "samba3" },
  { "time": 15.383, "move": "samba1" },
  { "time": 16.033, "move": "samba1" },
  { "time": 16.715, "move": "samba1" },
  { "time": 17.369, "move": "samba1" },
  { "time": 18.037, "move": "samba1" },
  { "time": 18.701, "move": "samba1" },
  { "time": 19.383, "move": "samba1" },
  { "time": 20.033, "move": "samba3" },
  { "time": 20.718, "move": "samba1" },
  { "time": 21.368, "move": "samba3" },
  { "time": 22.061, "move": "samba3" },
  { "time": 22.552, "move": "samba3" },
  { "time": 23.051, "move": "samba3" },
  { "time": 23.885, "move": "samba3" },
  { "time": 24.152, "move": "samba4" },
  { "time": 24.718, "move": "samba3" },
  { "time": 25.387, "move": "samba3" },
  { "time": 26.05, "move": "samba4" },
  { "time": 26.561, "move": "samba3" },
  { "time": 27.053, "move": "samba3" },
  { "time": 27.382, "move": "samba3" },
  { "time": 28.067, "move": "samba3" },
  { "time": 29.417, "move": "samba3" },
  { "time": 30.934, "move": "samba3" },
  { "time": 32.352, "move": "samba2" },
  { "time": 32.619, "move": "samba1" },
  { "time": 32.886, "move": "samba3" },
  { "time": 33.385, "move": "samba3" },
  { "time": 34.711, "move": "samba3" },
  { "time": 36.717, "move": "samba3" },
  { "time": 37.388, "move": "samba1" },
  { "time": 38.72, "move": "samba3" },
  { "time": 40.066, "move": "samba3" },
  { "time": 45.401, "move": "samba3" },
  { "time": 56.067, "move": "samba3" },
  { "time": 59.403, "move": "samba3" },
  { "time": 61.399, "move": "samba3" },
  { "time": 64.717, "move": "samba4" },
  { "time": 65.367, "move": "samba4" },
  { "time": 66.049, "move": "samba1" },
  { "time": 66.702, "move": "samba1" },
  { "time": 67.384, "move": "samba1" },
  { "time": 68.034, "move": "samba3" },
  { "time": 68.703, "move": "samba3" },
  { "time": 69.367, "move": "samba1" },
  { "time": 70.04, "move": "samba3" },
  { "time": 70.702, "move": "samba3" },
  { "time": 71.384, "move": "samba1" },
  { "time": 72.034, "move": "samba1" },
  { "time": 72.716, "move": "samba1" },
  { "time": 73.366, "move": "samba1" },
  { "time": 74.051, "move": "samba1" },
  { "time": 74.701, "move": "samba3" },
  { "time": 75.384, "move": "samba1" },
  { "time": 75.886, "move": "samba3" },
  { "time": 76.153, "move": "samba3" },
  { "time": 77.218, "move": "samba3" },
  { "time": 77.719, "move": "samba3" },
  { "time": 78.039, "move": "samba3" },
  { "time": 78.562, "move": "samba3" },
  { "time": 79.894, "move": "samba3" },
  { "time": 80.715, "move": "samba3" },
  { "time": 81.4, "move": "samba3" },
  { "time": 82.712, "move": "samba3" },
  { "time": 84.248, "move": "samba3" },
  { "time": 85.685, "move": "samba2" },
  { "time": 85.952, "move": "samba1" },
  { "time": 86.22, "move": "samba3" },
  { "time": 86.561, "move": "samba3" },
  { "time": 130.049, "move": "samba1" },
  { "time": 130.702, "move": "samba3" },
  { "time": 131.384, "move": "samba1" },
  { "time": 132.034, "move": "samba3" },
  { "time": 132.717, "move": "samba1" },
  { "time": 133.367, "move": "samba1" },
  { "time": 133.72, "move": "samba3" },
  { "time": 134.028, "move": "samba3" },
  { "time": 134.702, "move": "samba3" },
  { "time": 135.384, "move": "samba1" },
  { "time": 136.034, "move": "samba1" },
  { "time": 136.706, "move": "samba1" },
  { "time": 137.366, "move": "samba1" },
  { "time": 138.028, "move": "samba3" },
  { "time": 138.572, "move": "samba4" },
  { "time": 139.384, "move": "samba1" },
  { "time": 140.034, "move": "samba3" },
  { "time": 140.716, "move": "samba1" },
  { "time": 141.378, "move": "samba1" },
  { "time": 142.051, "move": "samba1" },
  { "time": 142.713, "move": "samba2" },
  { "time": 143.363, "move": "samba3" },
  { "time": 143.894, "move": "samba4" },
  { "time": 144.715, "move": "samba1" },
  { "time": 145.369, "move": "samba3" },
  { "time": 146.051, "move": "samba1" },
  { "time": 146.701, "move": "samba1" },
  { "time": 148.736, "move": "samba1" },
  { "time": 149.699, "move": "samba3" },
  { "time": 150.037, "move": "samba1" },
  { "time": 150.561, "move": "samba3" },
  { "time": 152.067, "move": "samba3" },
  { "time": 152.735, "move": "samba3" },
  { "time": 166.049, "move": "samba3" },
  { "time": 178.733, "move": "samba3" },
  { "time": 182.05, "move": "samba3" },
  { "time": 182.7, "move": "samba1" },
  { "time": 183.362, "move": "samba3" },
  { "time": 184.036, "move": "samba1" },
  { "time": 184.694, "move": "samba3" },
  { "time": 185.368, "move": "samba1" },
  { "time": 186.03, "move": "samba4" },
  { "time": 186.561, "move": "samba4" },
  { "time": 187.371, "move": "samba4" },
  { "time": 188.044, "move": "samba1" },
  { "time": 188.694, "move": "samba3" },
  { "time": 189.379, "move": "samba1" },
  { "time": 190.029, "move": "samba3" },
  { "time": 190.563, "move": "samba3" },
  { "time": 191.385, "move": "samba2" },
  { "time": 191.901, "move": "samba4" },
  { "time": 192.717, "move": "samba2" },
  { "time": 193.378, "move": "samba1" },
  { "time": 194.049, "move": "samba2" },
  { "time": 194.702, "move": "samba1" },
  { "time": 195.359, "move": "samba3" },
  { "time": 195.915, "move": "samba3" },
  { "time": 196.703, "move": "samba3" },
  { "time": 197.251, "move": "samba4" },
  { "time": 201.729, "move": "samba3" },
  { "time": 203.862, "move": "samba4" },
  { "time": 204.664, "move": "samba4" },
  { "time": 207.415, "move": "samba4" }
]